lfig/__init__.py
lfig/latex_figure.py
lfig-0.1.4.dist-info/LICENSE.txt
lfig-0.1.4.dist-info/METADATA
lfig-0.1.4.dist-info/WHEEL
lfig-0.1.4.dist-info/top_level.txt
lfig-0.1.4.dist-info/RECORD
