Metadata-Version: 2.1
Name: lfig
Version: 0.1.4
Summary: Latex figures from matplotlib
Home-page: https://github.com/flynnbr11/lfig-py
Author: Brian Flynn
Author-email: flynnbr@tcd.ie
License: MIT
License-File: LICENSE.txt
Requires-Dist: numpy
Requires-Dist: matplotlib
